smallneuron/__init__.py
smallneuron/build
smallneuron/gpio_h3.c
smallneuron/gpio_h3.h
smallneuron/gpio_h3.so
smallneuron/logger.py
smallneuron/smallneuron.py
smallneuron/sndummy.py
smallneuron/sngpio.py
smallneuron/sninput.py
smallneuron/snmqtt.py
smallneuron/snserial.py
smallneuron/sntimer.py
smallneuron/snwatcher.py
smallneuron-2.4.19.dist-info/licenses/LICENSE
smallneuron-2.4.19.dist-info/METADATA
smallneuron-2.4.19.dist-info/WHEEL
smallneuron-2.4.19.dist-info/top_level.txt
smallneuron-2.4.19.dist-info/RECORD
