Metadata-Version: 2.4
Name: smallneuron
Version: 2.4.19
Summary: Small Neuron Workflow
Author-email: Andres Artigas <andres@artigas.cl>
License-Expression: MIT
Project-URL: Homepage, https://github.com/pypa/sampleproject
Project-URL: Issues, https://github.com/pypa/sampleproject/issues
Classifier: Programming Language :: Python :: 3
Classifier: Operating System :: OS Independent
Requires-Python: >=3.7
License-File: LICENSE
Dynamic: license-file
